[
    {
        "wikidata_id": "Q16354713",
        "name": "Alytus College",
        "short_name": null,
        "official_website": "http:\/\/www.akolegija.lt\/",
        "aliases": null,
        "latitude": 54.399963,
        "longitude": 24.06759,
        "type": "college",
        "description": null
    },
    {
        "wikidata_id": "Q16458989",
        "name": "Babtai institute",
        "short_name": null,
        "official_website": null,
        "aliases": null,
        "latitude": 55.0818389,
        "longitude": 23.7984806,
        "type": "institute",
        "description": null
    },
    {
        "wikidata_id": "Q21148473",
        "name": "Baltic-American Biotaxonomy Institute",
        "short_name": null,
        "official_website": null,
        "aliases": null,
        "latitude": null,
        "longitude": null,
        "type": "institute",
        "description": null
    },
    {
        "wikidata_id": "Q30285236",
        "name": "Center for Physical Sciences and Technology",
        "short_name": null,
        "official_website": "https:\/\/www.ftmc.lt\/en\/",
        "aliases": [
            "FTMC"
        ],
        "latitude": 54.9172901,
        "longitude": 23.9064918,
        "type": "institute",
        "description": null
    },
    {
        "wikidata_id": "Q1779338",
        "name": "College of Social Sciences",
        "short_name": null,
        "official_website": "http:\/\/www.smk.lt\/",
        "aliases": [
            "SMK",
            "SMK University of Applied Social Sciences"
        ],
        "latitude": 55.699191,
        "longitude": 21.135579,
        "type": "college",
        "description": null
    },
    {
        "wikidata_id": "Q74538564",
        "name": "Doctoral Candidates' Association",
        "short_name": null,
        "official_website": null,
        "aliases": null,
        "latitude": null,
        "longitude": null,
        "type": "institute",
        "description": null
    },
    {
        "wikidata_id": "Q16458919",
        "name": "Ekonomikos institutas (Lietuvos TSR Mokslų akademija)",
        "short_name": null,
        "official_website": null,
        "aliases": null,
        "latitude": null,
        "longitude": null,
        "type": "institute",
        "description": null
    },
    {
        "wikidata_id": "Q74537176",
        "name": "Faculty of Philology, Department of Lithuanian Language",
        "short_name": null,
        "official_website": null,
        "aliases": null,
        "latitude": null,
        "longitude": null,
        "type": "institute",
        "description": null
    },
    {
        "wikidata_id": "Q74541762",
        "name": "Faculty of Social Sciences at Vytautas Magnus University",
        "short_name": null,
        "official_website": null,
        "aliases": null,
        "latitude": null,
        "longitude": null,
        "type": "institute",
        "description": null
    },
    {
        "wikidata_id": "Q12654580",
        "name": "Fizikos ir matematikos institutas",
        "short_name": null,
        "official_website": null,
        "aliases": [
            "Lietuvos TSR Mokslų akademija"
        ],
        "latitude": null,
        "longitude": null,
        "type": "institute",
        "description": null
    },
    {
        "wikidata_id": "Q1501626",
        "name": "General Jonas Žemaitis Military Academy of Lithuania",
        "short_name": null,
        "official_website": "http:\/\/www.lka.lt\/",
        "aliases": [
            "Military Academy of Lithuania"
        ],
        "latitude": 54.70234,
        "longitude": 25.313433,
        "type": "university",
        "description": "The General Jonas Žemaitis Military Academy of Lithuania (Generolo Jono Žemaičio Lietuvos karo akademija) is a state-sponsored institution of higher learning based in Vilnius, Lithuania. It was founded in 1994 by the Lithuanian Seimas, and is overseen by the Ministry of National Defense. It is named in honor of General Jonas Žemaitis, commander of the armed anti-Soviet resistance in Lithuania."
    },
    {
        "wikidata_id": "Q12655268",
        "name": "Geologijos ir geografijos institutas",
        "short_name": null,
        "official_website": null,
        "aliases": null,
        "latitude": null,
        "longitude": null,
        "type": "institute",
        "description": null
    },
    {
        "wikidata_id": "Q12649082",
        "name": "Institute of Architecture and Construction",
        "short_name": null,
        "official_website": "https:\/\/asi.ktu.edu\/",
        "aliases": null,
        "latitude": 54.8969444,
        "longitude": 23.9558333,
        "type": "institute",
        "description": null
    },
    {
        "wikidata_id": "Q12651278",
        "name": "Institute of Botany",
        "short_name": null,
        "official_website": null,
        "aliases": [
            "BILAS"
        ],
        "latitude": 54.71655,
        "longitude": 25.184249,
        "type": "institute",
        "description": null
    },
    {
        "wikidata_id": "Q12656737",
        "name": "Institute of Immunology",
        "short_name": null,
        "official_website": null,
        "aliases": null,
        "latitude": 54.7522222,
        "longitude": 25.2738889,
        "type": "institute",
        "description": null
    },
    {
        "wikidata_id": "Q15709822",
        "name": "Institute of Lithuanian Literature and Folklore",
        "short_name": null,
        "official_website": "http:\/\/www.llti.lt",
        "aliases": null,
        "latitude": 54.695264,
        "longitude": 25.305689,
        "type": "university",
        "description": "The Institute of Lithuanian Literature and Folklore (Lithuanian: Lietuvių literatūros ir tautosakos institutas)   is a scientific institution in Lithuania. It conducts research in Lithuanian literature and folklore. It resides in the former Vileišis Palace in Antakalnis district of Vilnius."
    },
    {
        "wikidata_id": "Q13638216",
        "name": "Institute of the Lithuanian Language",
        "short_name": null,
        "official_website": "http:\/\/www.lki.lt\/",
        "aliases": null,
        "latitude": 54.6951,
        "longitude": 25.3054,
        "type": "institute",
        "description": "The Institute of the Lithuanian Language (Lithuanian: Lietuvių kalbos institutas) in Vilnius is a state-funded research institute that focuses on research into the Lithuanian language. The Institute of the Lithuanian Language is a research establishment with longstanding traditions. Founded in Vilnius back in 1941 on the basis of the Institute for Lithuanian Studies of Antanas Smetona (which itself was founded in Kaunas in 1939 and relocated to Vilnius in 1940)."
    },
    {
        "wikidata_id": "Q1667287",
        "name": "International School of Law and Business",
        "short_name": null,
        "official_website": "http:\/\/www.islb.eu",
        "aliases": [
            "ISLB"
        ],
        "latitude": 54.700143,
        "longitude": 25.220769,
        "type": "university",
        "description": "Homo infinitum, formerly known as the  International School of Law and Business (ISLB, Lithuanian: Tarptautinė teisės ir verslo aukštoji mokykla or TTVAM) is a former private college in Vilnius (Laisvės prospektas 58, Viršuliškės), Lithuania. The ISLB closed down in July 2024, and subsequently lost its accreditation in 2025.\nISLB was founded on September 1, 1998, as Daugvilienė Business High School (Daugvilienės aukštesnioji verslo mokykla) and 2001 as the Vilnius Law and Business College (Vilniaus teisės ir verslo kolegija)."
    },
    {
        "wikidata_id": "Q1626754",
        "name": "ISM University of Management and Economics",
        "short_name": null,
        "official_website": "http:\/\/www.ism.lt\/",
        "aliases": null,
        "latitude": 54.6752778,
        "longitude": 25.2875,
        "type": "university",
        "description": "ISM University of Management and Economics (Lithuanian: ISM Vadybos ir ekonomikos universitetas) is an institution of undergraduate, graduate and post-graduate education in business, management and economics. The university serves as a centre of market analysis, executive training and academic thought.\nISM was established in Kaunas in 1999 as the first privately owned institution of management education in Lithuania."
    },
    {
        "wikidata_id": "Q16453881",
        "name": "Joniskelis Ignas Karpis school of agriculture and services",
        "short_name": null,
        "official_website": null,
        "aliases": null,
        "latitude": null,
        "longitude": null,
        "type": "college",
        "description": null
    },
    {
        "wikidata_id": "Q13580310",
        "name": "Kaunas College",
        "short_name": null,
        "official_website": "http:\/\/www.kaunokolegija.lt\/",
        "aliases": [
            "Kauno Kolegija",
            "Kauno Kolegija (Kaunas University of Applied Sciences)",
            "Kauno University of Applied Sciences"
        ],
        "latitude": 54.92,
        "longitude": 23.9844444,
        "type": "university",
        "description": null
    },
    {
        "wikidata_id": "Q12660045",
        "name": "Kaunas College of Technology",
        "short_name": null,
        "official_website": "http:\/\/www.ktk.lt\/",
        "aliases": [
            "KTK",
            "Kaunas Higher Technical School",
            "Kaunas University of Applied Engineering",
            "Kaunas University of Applied Engineering Sciences"
        ],
        "latitude": 54.9136111,
        "longitude": 23.9286111,
        "type": "college",
        "description": null
    },
    {
        "wikidata_id": "Q1489862",
        "name": "Kaunas Cultural Centre of Various Nations",
        "short_name": null,
        "official_website": "http:\/\/www.minority.lt\/",
        "aliases": null,
        "latitude": 54.8988889,
        "longitude": 23.8930556,
        "type": "university",
        "description": "Kaunas Cultural Centre of Various Nations is a cultural and educational institution intended to preserve the cultural identities of national minorities and encourage their positive integration into the Lithuanian society. The institution promotes international and national tolerance and strives to develop civil society."
    },
    {
        "wikidata_id": "Q15248060",
        "name": "Kaunas Forestry and Environmental Engineering College",
        "short_name": null,
        "official_website": "http:\/\/www.kmaik.lt\/",
        "aliases": [
            "Kaunas College of Forestry and Environmental Engineering",
            "KMAIK"
        ],
        "latitude": 54.8561111,
        "longitude": 24.0458333,
        "type": "college",
        "description": null
    },
    {
        "wikidata_id": "Q1353563",
        "name": "Kaunas Priest Seminary",
        "short_name": null,
        "official_website": "http:\/\/kks.lcn.lt\/index.php",
        "aliases": null,
        "latitude": 54.897,
        "longitude": 23.884,
        "type": "university",
        "description": "Kaunas Priest Seminary (Lithuanian: Kauno kunigų seminarija) is the largest seminary in Lithuania serving the Roman Catholic Archdiocese of Kaunas. It is part of the Faculty of Theology of Vytautas Magnus University. Its current rector is Aurelijus Žukauskas."
    },
    {
        "wikidata_id": "Q132734684",
        "name": "Kaunas State Vytautas Magnus University",
        "short_name": null,
        "official_website": null,
        "aliases": [
            "Kaunas National Vytautas Magnus University",
            "Kaunas State University",
            "Kaunas University",
            "Univeristy of Lithuania",
            "University of Kaunas",
            "University of Lithuania in Kaunas",
            "Vytautas Magnus University"
        ],
        "latitude": null,
        "longitude": null,
        "type": "university",
        "description": null
    },
    {
        "wikidata_id": "Q625158",
        "name": "Kaunas University of Technology",
        "short_name": null,
        "official_website": "https:\/\/ktu.edu\/",
        "aliases": [
            "Kaunas Antanas Sniečkus Polytechnic Institute",
            "Kaunas Polytechnic Institute"
        ],
        "latitude": 54.8988889,
        "longitude": 23.9125,
        "type": "university",
        "description": "The Kaunas University of Technology (abbreviated as KTU, Lithuanian: Kauno technologijos universitetas) is a public research university located in Kaunas, Lithuania. Established in 1922, KTU has been seen as one of Lithuania's top science education centers. In 2021, KTU was ranked the second-best university in Lithuania."
    },
    {
        "wikidata_id": "Q565119",
        "name": "Kauno Meno mokykla",
        "short_name": null,
        "official_website": "http:\/\/www.jvmf.lt\/",
        "aliases": null,
        "latitude": 54.9008333,
        "longitude": 23.9005556,
        "type": "university",
        "description": "Kaunas School of Arts (Lithuanian: Kauno meno mokykla) was a public art school, which operated from 1922 to 1940 in Kaunas, Lithuania. At the time, it was the only operating art school in Lithuania. The institution continued to exist (under other names) in the Lithuanian SSR, as well as in modern Lithuania, after the restoration of Latvian independence."
    },
    {
        "wikidata_id": "Q1737499",
        "name": "Kazimieras Simonavičius University",
        "short_name": null,
        "official_website": "http:\/\/www.ksu.lt",
        "aliases": null,
        "latitude": 54.6702778,
        "longitude": 25.2627778,
        "type": "university",
        "description": "Kazimieras Simonavičius University (previously: Vilnius Academy of Business Law (VABL), Lithuanian: Vilniaus verslo teisės akademija) is a private, state-accredited research university in Vilnius, Lithuania. The Ministry of Education and Science of the Republic of Lithuania licensed the former Vilnius Academy of Business Law on August 26, 2003. Teaching started in 2004."
    },
    {
        "wikidata_id": "Q103154262",
        "name": "Kazimiero Simonavičiaus universitetas Ekonomika",
        "short_name": null,
        "official_website": null,
        "aliases": null,
        "latitude": null,
        "longitude": null,
        "type": "university",
        "description": null
    },
    {
        "wikidata_id": "Q103154270",
        "name": "Kazimiero Simonavičiaus universitetas Integruota kūrybos komunikacija",
        "short_name": null,
        "official_website": null,
        "aliases": null,
        "latitude": null,
        "longitude": null,
        "type": "university",
        "description": null
    },
    {
        "wikidata_id": "Q103154279",
        "name": "Kazimiero Simonavičiaus universitetas Politikos mokslai",
        "short_name": null,
        "official_website": null,
        "aliases": null,
        "latitude": null,
        "longitude": null,
        "type": "university",
        "description": null
    },
    {
        "wikidata_id": "Q103154286",
        "name": "Kazimiero Simonavičiaus universitetas Sociologija",
        "short_name": null,
        "official_website": null,
        "aliases": null,
        "latitude": null,
        "longitude": null,
        "type": "university",
        "description": null
    },
    {
        "wikidata_id": "Q103154311",
        "name": "Kazimiero Simonavičiaus universitetas Viešasis administravimas",
        "short_name": null,
        "official_website": null,
        "aliases": null,
        "latitude": null,
        "longitude": null,
        "type": "university",
        "description": null
    },
    {
        "wikidata_id": "Q171932",
        "name": "Klaipeda State University of Applied Sciences",
        "short_name": null,
        "official_website": "http:\/\/www.kvk.lt\/",
        "aliases": [
            "Klaipėdos valstybinė kolegija",
            "KVK"
        ],
        "latitude": 55.72627,
        "longitude": 21.17135,
        "type": "college",
        "description": null
    },
    {
        "wikidata_id": "Q175686",
        "name": "Klaipėda Pedagogical Institute",
        "short_name": null,
        "official_website": null,
        "aliases": null,
        "latitude": 55.71948,
        "longitude": 21.13461,
        "type": "university",
        "description": null
    },
    {
        "wikidata_id": "Q178200",
        "name": "Klaipėda University",
        "short_name": null,
        "official_website": "http:\/\/www.ku.lt\/",
        "aliases": [
            "Klaipėdos Universitetas"
        ],
        "latitude": 55.7245833,
        "longitude": 21.1237778,
        "type": "university",
        "description": "Klaipėda University (Lithuanian: Klaipėdos universitetas or KU) is a university in the Lithuanian port city of Klaipėda."
    },
    {
        "wikidata_id": "Q12661027",
        "name": "Kolping College",
        "short_name": null,
        "official_website": "http:\/\/kolegija.kolping.lt\/",
        "aliases": [
            "Kolping University of Applied Sciences",
            "Kolpingo kolegija"
        ],
        "latitude": 54.898088,
        "longitude": 23.887088,
        "type": "college",
        "description": null
    },
    {
        "wikidata_id": "Q1584915",
        "name": "Law Institute of Lithuania",
        "short_name": null,
        "official_website": "http:\/\/www.teise.org\/",
        "aliases": null,
        "latitude": null,
        "longitude": null,
        "type": "institute",
        "description": "The Institute of Law (Lithuanian: Teisės institutas) is a law research establishment, founded in 1991 by the Government of the Republic of Lithuania seeking to coordinate the reform of the legal system and law institutions, to combine it with the economic and social reorganization carried in the country. The founder of the Institute is the Ministry of Justice of the Republic of Lithuania. The main areas of research interests of the Law Institute are as follows: public law (paying most attention to the problems of criminal law, constitutional law and criminal justice) and criminology."
    },
    {
        "wikidata_id": "Q1667494",
        "name": "LCC International University",
        "short_name": null,
        "official_website": "http:\/\/www.lcc.lt\/",
        "aliases": null,
        "latitude": 55.7311111,
        "longitude": 21.1333333,
        "type": "university",
        "description": "LCC International University, formerly Lithuania Christian College (LCC), is a liberal arts institution in the city of Klaipėda, Lithuania, established in 1991 by a joint venture of Lithuanian, Canadian and American foundations.\nIt is a member of the European Colleges of Liberal Arts and Sciences."
    },
    {
        "wikidata_id": "Q16458807",
        "name": "Lietuvos bibliografijos institutas",
        "short_name": null,
        "official_website": null,
        "aliases": null,
        "latitude": null,
        "longitude": null,
        "type": "institute",
        "description": null
    },
    {
        "wikidata_id": "Q12663374",
        "name": "Lietuvos kultūros tyrimų institutas",
        "short_name": null,
        "official_website": null,
        "aliases": null,
        "latitude": null,
        "longitude": null,
        "type": "institute",
        "description": null
    },
    {
        "wikidata_id": "Q1787936",
        "name": "Lithuanian Academy of Music and Theatre",
        "short_name": null,
        "official_website": "http:\/\/lmta.lt",
        "aliases": null,
        "latitude": 54.6885833,
        "longitude": 25.26975,
        "type": "university",
        "description": "The Lithuanian Academy of Music and Theatre in Vilnius, Lithuania, is a state-supported conservatory that trains students in music, theatre, and multimedia arts."
    },
    {
        "wikidata_id": "Q12663298",
        "name": "Lithuanian Energy Institute",
        "short_name": null,
        "official_website": "http:\/\/www.lei.lt\/",
        "aliases": [
            "LEI",
            "Lietuvos energetikos institutas"
        ],
        "latitude": 54.895,
        "longitude": 23.9541667,
        "type": "institute",
        "description": null
    },
    {
        "wikidata_id": "Q6648382",
        "name": "Lithuanian Institute of History",
        "short_name": null,
        "official_website": "http:\/\/www.istorija.lt",
        "aliases": null,
        "latitude": 54.6902287,
        "longitude": 25.2661507,
        "type": "institute",
        "description": "The Lithuanian Institute of History (Lithuanian: Lietuvos istorijos institutas) is a state-funded research institution in Lithuania. Governed by national law, it is the country's main institution of history research, concentrating mostly on the history of Lithuania and its neighbouring states.\nThe institute employs 126 people; 64 of them have Ph.D. degrees and 4 are habilitated doctors."
    },
    {
        "wikidata_id": "Q2264750",
        "name": "Lithuanian Maritime Academy",
        "short_name": null,
        "official_website": "http:\/\/www.lajm.lt\/",
        "aliases": [
            "LAJM",
            "Lithuanian Maritime College"
        ],
        "latitude": 55.71651,
        "longitude": 21.12456,
        "type": "university",
        "description": null
    },
    {
        "wikidata_id": "Q826358",
        "name": "Lithuanian Sports University",
        "short_name": null,
        "official_website": "http:\/\/www.lsu.lt\/",
        "aliases": [
            "Lietuvos Sporto Universitetas",
            "Lithuanian Academy of Physical Education"
        ],
        "latitude": 54.8983333,
        "longitude": 23.9344444,
        "type": "university",
        "description": "Lithuanian Sports University or LSU is a university in Kaunas, Lithuania, specializing in sports, physical activities, and physiology. It is headquartered in Žaliakalnis neighbourhood, in close proximity to the Kaunas Sports Hall and the S. Darius and S. Girėnas Stadium."
    },
    {
        "wikidata_id": "Q56860",
        "name": "Lithuanian University of Educational Sciences",
        "short_name": null,
        "official_website": "http:\/\/www.leu.lt\/",
        "aliases": [
            "Lietuvos edukologijos universitetas",
            "Vilniaus pedagoginis universitetas",
            "Lithuanian Pedagogical University"
        ],
        "latitude": 54.6964167,
        "longitude": 25.2624444,
        "type": "university",
        "description": null
    },
    {
        "wikidata_id": "Q2092640",
        "name": "Lithuanian University of Health Sciences",
        "short_name": null,
        "official_website": "https:\/\/lsmu.lt\/",
        "aliases": null,
        "latitude": 54.8941667,
        "longitude": 23.9163889,
        "type": "university",
        "description": "Lithuanian University of Health Sciences (Lithuanian: Lietuvos sveikatos mokslų universitetas, LSMU) is a medical school in Kaunas, Lithuania. The present-day Lithuanian University of Health Sciences is a consolidation of two institutions of higher education, Kaunas University of Medicine and the Lithuanian Veterinary Academy. It uses the Hospital of Lithuanian University of Health Sciences Kaunas Clinics and the Kaunas Red Cross Hospital as teaching hospitals."
    },
    {
        "wikidata_id": "Q1779334",
        "name": "Marijampole College",
        "short_name": null,
        "official_website": "http:\/\/www.marko.lt\/",
        "aliases": null,
        "latitude": 54.53281,
        "longitude": 23.350255,
        "type": "college",
        "description": "Marijampolė University of Applied Sciences (Lithuanian: Marijampolės kolegija, MARKO) is an institution of higher education located in Marijampolė, Lithuania. It was established in 2001 after merger of Marijampole Pedagogical High School, and Marijampole Agricultural High School. The university offers 9 undergraduate and 2 post-graduate courses."
    },
    {
        "wikidata_id": "Q12664739",
        "name": "Matematikos ir informatikos institutas (Lithuania)",
        "short_name": null,
        "official_website": null,
        "aliases": null,
        "latitude": null,
        "longitude": null,
        "type": "institute",
        "description": null
    },
    {
        "wikidata_id": "Q1247342",
        "name": "Mykolas Romeris University",
        "short_name": null,
        "official_website": "https:\/\/www.mruni.eu\/",
        "aliases": [
            "Mykolo Romerio universitetas"
        ],
        "latitude": 54.7338889,
        "longitude": 25.2588889,
        "type": "university",
        "description": "Mykolas Romeris University (MRU) is the largest specialized university for social sciences and humanities in Lithuania located in Vilnius, Kaunas and Marijampolė. It is named after the patriarch of Lithuania‘s Constitutional Law Professor Mykolas Romeris (1880-1945).\nMRU offers a wide range of social science study programs, making up 95% of its entire academic portfolio (according to the AIKOS database)."
    },
    {
        "wikidata_id": "Q15115554",
        "name": "National Cancer Institute",
        "short_name": null,
        "official_website": "http:\/\/www.nvi.lt\/",
        "aliases": [
            "Institute of Oncology"
        ],
        "latitude": 54.751818,
        "longitude": 25.282175,
        "type": "institute",
        "description": null
    },
    {
        "wikidata_id": "Q16478151",
        "name": "Northern Lithuania College",
        "short_name": null,
        "official_website": "http:\/\/www.slk.lt\/",
        "aliases": null,
        "latitude": 55.9108333,
        "longitude": 23.2741667,
        "type": "college",
        "description": null
    },
    {
        "wikidata_id": "Q15859710",
        "name": "Panevėžys College",
        "short_name": null,
        "official_website": "http:\/\/www.panko.lt\/",
        "aliases": null,
        "latitude": 55.7275,
        "longitude": 24.3616667,
        "type": "college",
        "description": null
    },
    {
        "wikidata_id": "Q16468849",
        "name": "Partijos istorijos institutas",
        "short_name": null,
        "official_website": null,
        "aliases": null,
        "latitude": 54.6871555,
        "longitude": 25.2796514,
        "type": "institute",
        "description": null
    },
    {
        "wikidata_id": "Q9366817",
        "name": "Polish University in Vilnius",
        "short_name": null,
        "official_website": "http:\/\/www.uspv.lt",
        "aliases": null,
        "latitude": 54.6741,
        "longitude": 25.2784,
        "type": "university",
        "description": null
    },
    {
        "wikidata_id": "Q12653934",
        "name": "Q12653934",
        "short_name": null,
        "official_website": null,
        "aliases": null,
        "latitude": null,
        "longitude": null,
        "type": "institute",
        "description": null
    },
    {
        "wikidata_id": "Q12654582",
        "name": "Q12654582",
        "short_name": null,
        "official_website": null,
        "aliases": null,
        "latitude": null,
        "longitude": null,
        "type": "institute",
        "description": null
    },
    {
        "wikidata_id": "Q12654878",
        "name": "Q12654878",
        "short_name": null,
        "official_website": null,
        "aliases": null,
        "latitude": null,
        "longitude": null,
        "type": "institute",
        "description": null
    },
    {
        "wikidata_id": "Q12656341",
        "name": "Q12656341",
        "short_name": null,
        "official_website": null,
        "aliases": null,
        "latitude": null,
        "longitude": null,
        "type": "institute",
        "description": null
    },
    {
        "wikidata_id": "Q12663488",
        "name": "Q12663488",
        "short_name": null,
        "official_website": null,
        "aliases": null,
        "latitude": null,
        "longitude": null,
        "type": "institute",
        "description": null
    },
    {
        "wikidata_id": "Q135465643",
        "name": "Q135465643",
        "short_name": null,
        "official_website": "https:\/\/www.hi.lt\/",
        "aliases": null,
        "latitude": 54.67875,
        "longitude": 25.285733,
        "type": "institute",
        "description": null
    },
    {
        "wikidata_id": "Q16443137",
        "name": "Q16443137",
        "short_name": null,
        "official_website": null,
        "aliases": null,
        "latitude": null,
        "longitude": null,
        "type": "institute",
        "description": null
    },
    {
        "wikidata_id": "Q16455766",
        "name": "Q16455766",
        "short_name": null,
        "official_website": null,
        "aliases": null,
        "latitude": 54.9177778,
        "longitude": 23.9961111,
        "type": "institute",
        "description": null
    },
    {
        "wikidata_id": "Q16458553",
        "name": "Q16458553",
        "short_name": null,
        "official_website": null,
        "aliases": null,
        "latitude": null,
        "longitude": null,
        "type": "institute",
        "description": null
    },
    {
        "wikidata_id": "Q16458554",
        "name": "Q16458554",
        "short_name": null,
        "official_website": null,
        "aliases": null,
        "latitude": null,
        "longitude": null,
        "type": "institute",
        "description": null
    },
    {
        "wikidata_id": "Q16459036",
        "name": "Q16459036",
        "short_name": null,
        "official_website": null,
        "aliases": null,
        "latitude": null,
        "longitude": null,
        "type": "institute",
        "description": null
    },
    {
        "wikidata_id": "Q16459049",
        "name": "Q16459049",
        "short_name": null,
        "official_website": null,
        "aliases": null,
        "latitude": null,
        "longitude": null,
        "type": "institute",
        "description": null
    },
    {
        "wikidata_id": "Q16464920",
        "name": "Q16464920",
        "short_name": null,
        "official_website": null,
        "aliases": null,
        "latitude": null,
        "longitude": null,
        "type": "institute",
        "description": null
    },
    {
        "wikidata_id": "Q18412215",
        "name": "Q18412215",
        "short_name": null,
        "official_website": "http:\/\/www.vtdko.lt\/gtf-naujienos",
        "aliases": null,
        "latitude": 54.70581,
        "longitude": 25.31019,
        "type": "university",
        "description": null
    },
    {
        "wikidata_id": "Q25494690",
        "name": "Q25494690",
        "short_name": null,
        "official_website": null,
        "aliases": null,
        "latitude": null,
        "longitude": null,
        "type": "institute",
        "description": null
    },
    {
        "wikidata_id": "Q12663398",
        "name": "Research Council of Lithuania",
        "short_name": null,
        "official_website": "http:\/\/www.lmt.lt\/",
        "aliases": [
            "LMT",
            "Lietuvos Mokslo Taryba",
            "lmt.lt"
        ],
        "latitude": 54.6871555,
        "longitude": 25.2796514,
        "type": "institute",
        "description": null
    },
    {
        "wikidata_id": "Q12670505",
        "name": "Semiconductor Physics Institute",
        "short_name": null,
        "official_website": "http:\/\/www.pfi.lt\/",
        "aliases": null,
        "latitude": null,
        "longitude": null,
        "type": "institute",
        "description": null
    },
    {
        "wikidata_id": "Q16472825",
        "name": "Socialinių tyrimų institutas",
        "short_name": null,
        "official_website": null,
        "aliases": null,
        "latitude": null,
        "longitude": null,
        "type": "institute",
        "description": null
    },
    {
        "wikidata_id": "Q74528376",
        "name": "Taras Shevchenko National University of Kyiv; Vilnius University",
        "short_name": null,
        "official_website": null,
        "aliases": null,
        "latitude": null,
        "longitude": null,
        "type": "institute",
        "description": null
    },
    {
        "wikidata_id": "Q1967259",
        "name": "Tarbut",
        "short_name": null,
        "official_website": null,
        "aliases": null,
        "latitude": null,
        "longitude": null,
        "type": "university",
        "description": "The word Tarbut (תרבות) means \"Culture\" in Hebrew.\nThe Tarbut movement was a network of secular, Hebrew-language schools in parts of the former Jewish Pale of Settlement, specifically in Poland, Romania and Lithuania. It operated primarily between the world wars."
    },
    {
        "wikidata_id": "Q866107",
        "name": "Telšiai Bishop Vincentas Borisevičius Priest Seminary",
        "short_name": null,
        "official_website": "http:\/\/www.tks.lt\/",
        "aliases": null,
        "latitude": 55.982694,
        "longitude": 22.245347,
        "type": "university",
        "description": null
    },
    {
        "wikidata_id": "Q1431447",
        "name": "Utenos kolegija Higher Education Institution",
        "short_name": null,
        "official_website": "https:\/\/www.utenos-kolegija.lt\/",
        "aliases": [
            "Utena College",
            "Utena University of Applied Sciences"
        ],
        "latitude": 55.4991944,
        "longitude": 25.6013889,
        "type": "college",
        "description": null
    },
    {
        "wikidata_id": "Q119132040",
        "name": "Vilniaus mažasis teatras",
        "short_name": null,
        "official_website": null,
        "aliases": [
            "Vilnius Small Theater"
        ],
        "latitude": 54.68725,
        "longitude": 25.27712,
        "type": "university",
        "description": null
    },
    {
        "wikidata_id": "Q1476319",
        "name": "Vilnius Academy of Art",
        "short_name": null,
        "official_website": "http:\/\/www.vda.lt\/",
        "aliases": [
            "Vilnius Academy of Arts"
        ],
        "latitude": null,
        "longitude": null,
        "type": "university",
        "description": null
    },
    {
        "wikidata_id": "Q12677532",
        "name": "Vilnius College",
        "short_name": null,
        "official_website": "https:\/\/www.viko.lt\/",
        "aliases": [
            "College of Vilnius"
        ],
        "latitude": 54.696111,
        "longitude": 25.256944,
        "type": "college",
        "description": null
    },
    {
        "wikidata_id": "Q12677534",
        "name": "Vilnius Cooperative College",
        "short_name": null,
        "official_website": "https:\/\/www.vkk.lt\/",
        "aliases": null,
        "latitude": 54.697222,
        "longitude": 25.275,
        "type": "college",
        "description": null
    },
    {
        "wikidata_id": "Q389852",
        "name": "Vilnius Gediminas Technical University",
        "short_name": null,
        "official_website": "http:\/\/www.vgtu.lt\/",
        "aliases": [
            "VGTU",
            "Vilniaus Gedimino Technikos Universiteta",
            "Vilnius Tech"
        ],
        "latitude": 54.7222222,
        "longitude": 25.3358333,
        "type": "university",
        "description": null
    },
    {
        "wikidata_id": "Q74544931",
        "name": "Vilnius Gediminas Technical University",
        "short_name": null,
        "official_website": null,
        "aliases": null,
        "latitude": null,
        "longitude": null,
        "type": "institute",
        "description": null
    },
    {
        "wikidata_id": "Q1355626",
        "name": "Vilnius St. Joseph Seminary",
        "short_name": null,
        "official_website": "https:\/\/www.seminarija.lt\/",
        "aliases": [
            "Vilniaus šv. Juozapo kunigų seminarija"
        ],
        "latitude": 54.7381,
        "longitude": 25.2786,
        "type": "university",
        "description": null
    },
    {
        "wikidata_id": "Q658192",
        "name": "Vilnius University",
        "short_name": null,
        "official_website": "https:\/\/www.vu.lt\/",
        "aliases": [
            "Universitas Vilnensis",
            "Vilniaus universitetas",
            "Vilniaus Universitetas",
            "vu.lt"
        ],
        "latitude": 54.6825,
        "longitude": 25.2872222,
        "type": "university",
        "description": null
    },
    {
        "wikidata_id": "Q12677592",
        "name": "Vilnius University Business School",
        "short_name": null,
        "official_website": "https:\/\/www.vm.vu.lt\/",
        "aliases": null,
        "latitude": 54.725,
        "longitude": 25.3364,
        "type": "university",
        "description": null
    },
    {
        "wikidata_id": "Q14634723",
        "name": "Vilnius University Faculty of Philology",
        "short_name": null,
        "official_website": "https:\/\/www.flf.vu.lt\/",
        "aliases": [
            "Vilnius University, Faculty of Philology"
        ],
        "latitude": 54.6830828,
        "longitude": 25.2871832,
        "type": "institute",
        "description": null
    },
    {
        "wikidata_id": "Q130745363",
        "name": "Vilnius University Institute of Data Science and Digital Technologies",
        "short_name": null,
        "official_website": "https:\/\/www.mii.lt\/",
        "aliases": [
            "Institute of Data Science and Digital Technologies",
            "Institute of Data Science and Digital technologies, Vilnius University"
        ],
        "latitude": null,
        "longitude": null,
        "type": "institute",
        "description": null
    },
    {
        "wikidata_id": "Q1756541",
        "name": "Vytautas Magnus University",
        "short_name": null,
        "official_website": "https:\/\/www.vdu.lt",
        "aliases": [
            "vdu.lt",
            "Vytautas Magnus University in Kaunas",
            "Vytauto Didžiojo Universitetas"
        ],
        "latitude": 54.8983333,
        "longitude": 23.9138889,
        "type": "university",
        "description": null
    },
    {
        "wikidata_id": "Q1479914",
        "name": "Vytautas Magnus University Agriculture Academy",
        "short_name": null,
        "official_website": "http:\/\/www.asu.lt\/",
        "aliases": [
            "Lithuanian Academy of Agriculture",
            "Aleksandras Stulginskis University",
            "Lithuanian University of Agriculture"
        ],
        "latitude": 54.8938611,
        "longitude": 23.8353056,
        "type": "university",
        "description": null
    },
    {
        "wikidata_id": "Q1263211",
        "name": "Zemaitija College",
        "short_name": null,
        "official_website": "http:\/\/www.zemko.lt\/",
        "aliases": null,
        "latitude": 55.729644,
        "longitude": 21.928911,
        "type": "college",
        "description": null
    },
    {
        "wikidata_id": "Q2324588",
        "name": "Šiauliai State College",
        "short_name": null,
        "official_website": "http:\/\/www.svako.lt\/",
        "aliases": null,
        "latitude": null,
        "longitude": null,
        "type": "college",
        "description": null
    },
    {
        "wikidata_id": "Q1784353",
        "name": "Šiauliai University",
        "short_name": null,
        "official_website": "http:\/\/www.su.lt\/en",
        "aliases": null,
        "latitude": 55.9264167,
        "longitude": 23.3244722,
        "type": "university",
        "description": null
    },
    {
        "wikidata_id": "Q25303227",
        "name": "Žiburėlis",
        "short_name": null,
        "official_website": null,
        "aliases": null,
        "latitude": null,
        "longitude": null,
        "type": "university",
        "description": null
    }
]
